[
	{
		"id":"1",
		"name":"寡言花瓶萌",
		"num":"12320 张"
	},
	{
		"id":"2",
		"name":"閒人勿進",
		"num":"2961 张"
	},
	{
		"id":"3",
		"name":"Big Bos",
		"num":"2675 张"
	},
	{
		"id":"4",
		"name":"-美麗的shi",
		"num":"1800 张"
	},
	{
		"id":"5",
		"name":"牛黑正",
		"num":"1588 张"
	},
	{
		"id":"6",
		"name":"兰斯洛",
		"num":"1575 张"
	},
	{
		"id":"7",
		"name":"叶霖箫",
		"num":"1505 张"
	},
	{
		"id":"8",
		"name":"紋",
		"num":"1414 张"
	},
	{
		"id":"9",
		"name":"黑姬",
		"num":"1243 张"
	},
	{
		"id":"10",
		"name":"温柔的电壶",
		"num":"1200 张"
	}
]
